<?xml version="1.0" encoding="UTF-8" ?>
<!DOCTYPE mapper
        PUBLIC "-//mybatis.org//DTD Mapper 3.0//EN"
        "http://mybatis.org/dtd/mybatis-3-mapper.dtd">
<mapper namespace="logistics.work.models.dao.WorkScheduleDao">
    <select id="queryWorkScheduleByDate" parameterType="java.util.Map"
            resultType="logistics.work.models.dto.WorkScheduleDto">
        select *
        from work_schedule
        where user_id=#{userId} and date_format(`date`,'%e %b %y') = date_format(#{date}, '%e %b %y')
    </select>
    <select id="queryWorkScheduleDetailByScheduleId" parameterType="Integer"
            resultType="logistics.work.models.dto.WorkScheduleDetailDto">
        select
        wsd.id,
        wp.work_name,
        wp.work_content,
        wp.work_instructor,
        wp.work_minutes,
        sc1.name as work_from,
        sc.name as finish_status,
        wsd.finish_picture,
        wsd.finish_feedback,
        wsd.finish_condition,
        wsd.finish_time
        from work_schedule_detail as wsd
        left join sys_config as sc1
        on wsd.work_from=sc1.`code`
        left join work_pool as wp
        on wsd.work_id=wp.id
        left join sys_config as sc
        on wsd.finish_status=sc.`code`
        <where>
            user_id=#{userId}
            and schedule_id=#{scheduleId}
            <if test="workFrom!=null">
                and wsd.work_from=#{workFrom}
            </if>
            <if test="workName!=null">
                and work_name like "%"#{workName}"%"
            </if>
            <if test="finishStatus!=null">
                and wsd.finish_status like #{finishStatus}
            </if>
        </where>
        order by wsd.finish_time asc
    </select>
    <update id="updateScheduleDetail" parameterType="logistics.work.models.dto.WorkScheduleDetailDto">
        update work_schedule_detail
        set finish_status=
        <foreach collection="list" item="item" index="index"
                 separator=" " open="case id" close="end">
            when #{item.id} then #{item.finishStatus}
        </foreach>,
        finish_picture=
        <foreach collection="list" item="item" index="index"
                 separator=" " open="case id" close="end">
            when #{item.id} then #{item.finishPicture}
        </foreach>,
        finish_condition=
        <foreach collection="list" item="item" index="index"
                 separator=" " open="case id" close="end">
            when #{item.id} then #{item.finishCondition}
        </foreach>,
        finish_feedback=
        <foreach collection="list" item="item" index="index"
                 separator=" " open="case id" close="end">
            when #{item.id} then #{item.finishFeedback}
        </foreach>,
        finish_time=
        <foreach collection="list" item="item" index="index"
                 separator=" " open="case id" close="end">
            when #{item.id} then #{item.finishTime}
        </foreach>
        where id in
        <foreach collection="list" index="index" item="item"
                 separator="," open="(" close=")">
            #{item.id}
        </foreach>
    </update>
    <update id="updateSchedule" parameterType="logistics.work.models.dto.WorkScheduleDto">
        update work_schedule
        set submit_time=NOW(),submit_status='submitted'
        where id=#{scheduleId}
    </update>
    <insert id="addSchedule" parameterType="logistics.work.models.domain.WorkSchedule" useGeneratedKeys="true"
            keyProperty="id">
        insert into work_schedule(user_id,`date`)
        values(#{userId},NOW())
    </insert>
    <insert id="addScheduleDetail">
        insert into work_schedule_detail(schedule_id,work_id,work_from)
        values
        <foreach collection="idList" separator="," item="id">
            (#{scheduleId},#{id},'w3')
        </foreach>
    </insert>
    <select id="queryTodayScheduleId" parameterType="Integer" resultType="Integer">
        select id
        from work_schedule as ws
        where date_format(ws.date,'%e %b %y') = date_format(now(), '%e %b %y') and ws.user_id=#{userId}
    </select>
    <select id="leaderQuerySchedule" parameterType="java.util.Map"
            resultType="logistics.work.models.dto.WorkScheduleDto">
        select *
        from work_schedule
        <where>
            <if test="employeeId!=null">
                user_id=#{employeeId}
            </if>
            <if test="date!=null">
                and date_format(`date`,'%e %b %y') = date_format(#{date}, '%e %b %y')
            </if>
        </where>
    </select>
    <select id="leaderQueryScheduleDetail" resultType="logistics.work.models.dto.WorkScheduleDetailDto"
            parameterType="java.util.Map">
        select
        wsd.id,
        wp.work_name,
        wp.work_content,
        wp.work_instructor,
        wp.work_minutes,
        sc1.name as work_from,
        sc.name as finish_status,
        wsd.finish_picture,
        wsd.finish_feedback,
        wsd.finish_condition,
        wsd.finish_time
        from work_schedule_detail as wsd
        left join sys_config as sc1
        on wsd.work_from=sc1.`code`
        left join work_pool as wp
        on wsd.work_id=wp.id
        left join sys_config as sc
        on wsd.finish_status=sc.`code`
        <where>
            <if test="employeeId!=null">
                user_id=#{employeeId}
            </if>
            <if test="scheduleId!=null">
                and schedule_id=#{scheduleId}
            </if>
        </where>
        order by wsd.finish_time asc
        limit #{pageStart},#{pageSize}
    </select>
    <select id="leaderQueryScheduleDetailCount" resultType="Integer" parameterType="java.util.Map">
        select
        count(*)
        from work_schedule_detail as wsd
        left join sys_config as sc1
        on wsd.work_from=sc1.`code`
        left join work_pool as wp
        on wsd.work_id=wp.id
        left join sys_config as sc
        on wsd.finish_status=sc.`code`
        <where>
            <if test="employeeId!=null">
                user_id=#{employeeId}
            </if>
            <if test="scheduleId!=null">
                and schedule_id=#{scheduleId}
            </if>
        </where>
    </select>
</mapper>